chatrelater/__init__.py
chatrelater/analyzer.py
chatrelater/analyzer_cli.py
chatrelater/nicknames.py
chatrelater/serialization.py
chatrelater/visualization.py
chatrelater/visualization_cli.py
ChatRelater-0.4.dist-info/LICENSE
ChatRelater-0.4.dist-info/METADATA
ChatRelater-0.4.dist-info/WHEEL
ChatRelater-0.4.dist-info/entry_points.txt
ChatRelater-0.4.dist-info/top_level.txt
ChatRelater-0.4.dist-info/RECORD
