Metadata-Version: 2.1
Name: ChatRelater
Version: 0.4
Summary: Analyze and visualize relations between chat users.
Home-page: http://homework.nwsnet.de/releases/1856/#chat-relater
Author: Jochen Kupperschmidt
Author-email: homework@nwsnet.de
License: MIT
Keywords: graphviz,irc,visualization
Platform: any
Classifier: Environment :: Console
Classifier: License :: OSI Approved :: MIT License
Classifier: Natural Language :: English
Classifier: Operating System :: OS Independent
Classifier: Programming Language :: Python
Classifier: Programming Language :: Python :: 3.7
Classifier: Programming Language :: Python :: 3.8
Classifier: Programming Language :: Python :: 3.9
Classifier: Topic :: Communications :: Chat
Classifier: Topic :: Internet :: Log Analysis
Requires-Python: >=3.7
Requires-Dist: graphviz (>=0.15)
